nbstata/__init__.py
nbstata/__main__.py
nbstata/_modidx.py
nbstata/browse.py
nbstata/cell.py
nbstata/code_utils.py
nbstata/completion_env.py
nbstata/completions.py
nbstata/config.py
nbstata/inspect.py
nbstata/install.py
nbstata/kernel.py
nbstata/logo-64x64.png
nbstata/magics.py
nbstata/misc_utils.py
nbstata/noecho.py
nbstata/pandas.py
nbstata/stata.py
nbstata/stata_more.py
nbstata/stata_session.py
nbstata/__pycache__/__init__.cpython-310.pyc
nbstata/__pycache__/__init__.cpython-311.pyc
nbstata/__pycache__/__main__.cpython-310.pyc
nbstata/__pycache__/__main__.cpython-311.pyc
nbstata/__pycache__/_modidx.cpython-310.pyc
nbstata/__pycache__/_modidx.cpython-311.pyc
nbstata/__pycache__/browse.cpython-310.pyc
nbstata/__pycache__/browse.cpython-311.pyc
nbstata/__pycache__/cell.cpython-310.pyc
nbstata/__pycache__/cell.cpython-311.pyc
nbstata/__pycache__/code_utils.cpython-310.pyc
nbstata/__pycache__/code_utils.cpython-311.pyc
nbstata/__pycache__/completion_env.cpython-310.pyc
nbstata/__pycache__/completion_env.cpython-311.pyc
nbstata/__pycache__/completions.cpython-310.pyc
nbstata/__pycache__/completions.cpython-311.pyc
nbstata/__pycache__/config.cpython-310.pyc
nbstata/__pycache__/config.cpython-311.pyc
nbstata/__pycache__/helpers.cpython-310.pyc
nbstata/__pycache__/helpers.cpython-311.pyc
nbstata/__pycache__/inspect.cpython-310.pyc
nbstata/__pycache__/inspect.cpython-311.pyc
nbstata/__pycache__/install.cpython-310.pyc
nbstata/__pycache__/install.cpython-311.pyc
nbstata/__pycache__/kernel.cpython-310.pyc
nbstata/__pycache__/kernel.cpython-311.pyc
nbstata/__pycache__/magics.cpython-310.pyc
nbstata/__pycache__/magics.cpython-311.pyc
nbstata/__pycache__/misc_utils.cpython-310.pyc
nbstata/__pycache__/misc_utils.cpython-311.pyc
nbstata/__pycache__/noecho.cpython-310.pyc
nbstata/__pycache__/noecho.cpython-311.pyc
nbstata/__pycache__/pandas.cpython-310.pyc
nbstata/__pycache__/pandas.cpython-311.pyc
nbstata/__pycache__/parsers.cpython-311.pyc
nbstata-0.8.3.dist-info/LICENSE
nbstata-0.8.3.dist-info/METADATA
nbstata-0.8.3.dist-info/WHEEL
nbstata-0.8.3.dist-info/entry_points.txt
nbstata-0.8.3.dist-info/top_level.txt
nbstata-0.8.3.dist-info/RECORD
