Metadata-Version: 2.1
Name: nbstata
Version: 0.8.3
Summary: Jupyter kernel for Stata built on pystata
Home-page: https://github.com/hugetim/nbstata
Author: Tim Huegerich
Author-email: hugetim@gmail.com
License: GNU General Public License v3
Keywords: nbdev jupyter notebook python stata
Classifier: Development Status :: 4 - Beta
Classifier: Intended Audience :: Science/Research
Classifier: Natural Language :: English
Classifier: Programming Language :: Python :: 3.9
Classifier: Programming Language :: Python :: 3.10
Classifier: License :: OSI Approved :: GNU General Public License v3 (GPLv3)
Requires-Python: >=3.9
License-File: LICENSE
Requires-Dist: jupyter-client
Requires-Dist: ipython
Requires-Dist: ipykernel
Requires-Dist: packaging
Requires-Dist: pandas
Requires-Dist: numpy
Requires-Dist: beautifulsoup4
Requires-Dist: fastcore
Requires-Dist: pygments (>=2.8)
Requires-Dist: ipydatagrid (<1.3)
Provides-Extra: dev
